subscriber/__init__.py
subscriber/podaac_access.py
subscriber/podaac_data_downloader.py
subscriber/podaac_data_subscriber.py
subscriber/subsetting.py
subscriber/token_formatter.py
podaac_data_subscriber-1.15.2.dist-info/LICENSE
podaac_data_subscriber-1.15.2.dist-info/METADATA
podaac_data_subscriber-1.15.2.dist-info/WHEEL
podaac_data_subscriber-1.15.2.dist-info/entry_points.txt
podaac_data_subscriber-1.15.2.dist-info/RECORD
