Metadata-Version: 2.1
Name: podaac-data-subscriber
Version: 1.15.2
Summary: PO.DAAC Data Subscriber Command Line Tool
Home-page: https://github.com/podaac/data-subscriber
License: Apache-2.0
Author: PO.DAAC
Author-email: podaac@podaac.jpl.nasa.gov
Requires-Python: >=3.7,<4.0
Classifier: License :: OSI Approved :: Apache Software License
Classifier: Programming Language :: Python :: 3
Classifier: Programming Language :: Python :: 3.7
Classifier: Programming Language :: Python :: 3.8
Classifier: Programming Language :: Python :: 3.9
Classifier: Programming Language :: Python :: 3.10
Classifier: Programming Language :: Python :: 3.11
Requires-Dist: harmony-py (>=0.4.12,<0.5.0)
Requires-Dist: packaging (>=23.0,<24.0)
Requires-Dist: requests (>=2.27.1,<3.0.0)
Requires-Dist: tenacity (>=8.0.1,<9.0.0)
Project-URL: Repository, https://github.com/podaac/data-subscriber
